torchgpipe_balancing.py
torchgpipe/__init__.py
torchgpipe/__version__.py
torchgpipe/batchnorm.py
torchgpipe/checkpoint.py
torchgpipe/copy.py
torchgpipe/dependency.py
torchgpipe/gpipe.py
torchgpipe/microbatch.py
torchgpipe/phony.py
torchgpipe/pipeline.py
torchgpipe/py.typed
torchgpipe/stream.py
torchgpipe/worker.py
torchgpipe/balance/__init__.py
torchgpipe/balance/blockpartition.py
torchgpipe/balance/profile.py
torchgpipe/skip/__init__.py
torchgpipe/skip/layout.py
torchgpipe/skip/namespace.py
torchgpipe/skip/portal.py
torchgpipe/skip/skippable.py
torchgpipe/skip/tracker.py
torchgpipe-0.0.7.dist-info/LICENSE
torchgpipe-0.0.7.dist-info/METADATA
torchgpipe-0.0.7.dist-info/NOTICE
torchgpipe-0.0.7.dist-info/WHEEL
torchgpipe-0.0.7.dist-info/top_level.txt
torchgpipe-0.0.7.dist-info/RECORD
