Metadata-Version: 2.1
Name: torchgpipe
Version: 0.0.7
Summary: GPipe for PyTorch
Home-page: https://github.com/kakaobrain/torchgpipe
Author: Kakao Brain
Maintainer: Heungsub Lee, Myungryong Jeong, Chiheon Kim
License: BSD-3-Clause
Keywords: pytorch gpipe
Platform: UNKNOWN
Classifier: Development Status :: 3 - Alpha
Classifier: Intended Audience :: Science/Research
Classifier: License :: OSI Approved :: BSD License
Classifier: Programming Language :: Python :: 3
Classifier: Programming Language :: Python :: 3.6
Classifier: Programming Language :: Python :: 3.7
Classifier: Programming Language :: Python :: 3 :: Only
Classifier: Topic :: Scientific/Engineering :: Artificial Intelligence
Classifier: Typing :: Typed
Requires-Dist: torch (>=1.1)
